{"state":"NC","stateName":"North Carolina","districts":{"congressional":[{"name":"Congressional District 1","center":[-77.0013,35.9001],"bounds":[[-78.5464,35.3473],[-76.0114,36.5521]]},{"name":"Congressional District 2","center":[-78.6393,35.8159],"bounds":[[-78.947,35.7246],[-78.2538,36.0764]]},{"name":"Congressional District 3","center":[-76.8305,35.2851],"bounds":[[-78.6723,34.4409],[-75.4606,36.551]]},{"name":"Congressional District 4","center":[-78.9374,36.2085],"bounds":[[-79.5424,35.8433],[-78.4535,36.5425]]},{"name":"Congressional District 5","center":[-81.3464,36.0471],"bounds":[[-82.4167,35.7428],[-80.0273,36.5881]]},{"name":"Congressional District 6","center":[-79.849,36.191],"bounds":[[-80.2611,35.8999],[-79.1432,36.5428]]},{"name":"Congressional District 7","center":[-78.5484,34.7834],"bounds":[[-79.4616,33.8423],[-77.5184,35.2669]]},{"name":"Congressional District 8","center":[-80.273,35.3724],"bounds":[[-80.8404,34.805],[-79.5979,36.0268]]},{"name":"Congressional District 9","center":[-79.2439,35.2228],"bounds":[[-80.0668,34.6303],[-78.7829,35.9207]]},{"name":"Congressional District 10","center":[-81.4922,35.6278],"bounds":[[-81.9869,35.1634],[-80.6932,36.0588]]},{"name":"Congressional District 11","center":[-82.7087,35.5985],"bounds":[[-84.3219,34.9866],[-81.8241,36.0845]]},{"name":"Congressional District 12","center":[-80.7484,35.3237],"bounds":[[-81.0039,35.1034],[-80.5399,35.5148]]},{"name":"Congressional District 13","center":[-78.5658,35.5063],"bounds":[[-79.0766,35.1751],[-77.9301,35.8181]]},{"name":"Congressional District 14","center":[-81.0188,35.2368],"bounds":[[-81.328,35.0016],[-80.6814,35.4098]]}],"state_senate":[{"name":"State Senate District 1","center":[-76.369,35.3717],"bounds":[[-77.1678,34.5916],[-75.4606,36.5107]]},{"name":"State Senate District 2","center":[-77.0562,35.3474],"bounds":[[-77.8342,34.8089],[-76.4689,35.7395]]},{"name":"State Senate District 3","center":[-76.8433,36.1126],"bounds":[[-78.324,35.598],[-75.7733,36.5521]]},{"name":"State Senate District 4","center":[-77.8214,35.4432],"bounds":[[-78.3066,35.1466],[-77.4743,35.8672]]},{"name":"State Senate District 5","center":[-77.4186,35.7312],"bounds":[[-77.8284,35.3277],[-77.0846,36.1545]]},{"name":"State Senate District 6","center":[-77.262,34.7494],"bounds":[[-77.6801,34.4409],[-77.1052,34.9845]]},{"name":"State Senate District 7","center":[-77.9123,34.2569],"bounds":[[-78.0299,33.9292],[-77.7105,34.3894]]},{"name":"State Senate District 8","center":[-78.4798,34.2719],"bounds":[[-79.0712,33.8423],[-77.9118,34.4848]]},{"name":"State Senate District 9","center":[-78.095,34.7881],"bounds":[[-78.902,34.2926],[-77.0472,35.2876]]},{"name":"State Senate District 10","center":[-78.3497,35.5255],"bounds":[[-78.7089,35.2547],[-78.0648,35.8181]]},{"name":"State Senate District 11","center":[-78.1099,36.113],"bounds":[[-78.5464,35.7279],[-77.698,36.5438]]},{"name":"State Senate District 12","center":[-78.9592,35.396],"bounds":[[-79.3599,35.1916],[-78.4492,35.6283]]},{"name":"State Senate District 13","center":[-78.6249,35.8817],"bounds":[[-78.802,35.8027],[-78.5261,35.9689]]},{"name":"State Senate District 14","center":[-78.5324,35.7655],"bounds":[[-78.6529,35.6253],[-78.2538,35.9365]]},{"name":"State Senate District 15","center":[-78.6906,35.7525],"bounds":[[-78.7951,35.654],[-78.5826,35.8626]]},{"name":"State Senate District 16","center":[-78.8145,35.8137],"bounds":[[-78.9363,35.7236],[-78.7105,35.9276]]},{"name":"State Senate District 17","center":[-78.7404,35.6797],"bounds":[[-78.995,35.5195],[-78.5666,35.7789]]},{"name":"State Senate District 18","center":[-78.5736,36.1039],"bounds":[[-78.8075,35.8543],[-78.3868,36.5425]]},{"name":"State Senate District 19","center":[-78.7683,35.0714],"bounds":[[-79.0916,34.8349],[-78.4947,35.2669]]},{"name":"State Senate District 20","center":[-79.0781,35.7485],"bounds":[[-79.5558,35.515],[-78.805,35.9905]]},{"name":"State Senate District 21","center":[-79.2506,35.2002],"bounds":[[-79.768,35.043],[-78.83,35.518]]},{"name":"State Senate District 22","center":[-78.8631,36.005],"bounds":[[-79.0007,35.9184],[-78.6998,36.2393]]},{"name":"State Senate District 23","center":[-79.1669,36.1732],"bounds":[[-79.5319,35.8608],[-78.7948,36.5422]]},{"name":"State Senate District 24","center":[-79.0967,34.7562],"bounds":[[-79.6929,34.2993],[-78.8054,35.2138]]},{"name":"State Senate District 25","center":[-79.5598,35.9084],"bounds":[[-79.9254,35.7055],[-79.2366,36.2497]]},{"name":"State Senate District 26","center":[-79.7879,36.1424],"bounds":[[-80.0388,35.8999],[-79.5136,36.5428]]},{"name":"State Senate District 27","center":[-79.9056,36.0481],"bounds":[[-80.0469,35.9068],[-79.7075,36.1506]]},{"name":"State Senate District 28","center":[-79.7858,36.0859],"bounds":[[-79.8976,36.0004],[-79.7124,36.1601]]},{"name":"State Senate District 29","center":[-80.0528,35.1907],"bounds":[[-80.7975,34.805],[-79.4588,35.9207]]},{"name":"State Senate District 30","center":[-80.3894,35.8175],"bounds":[[-80.7078,35.5041],[-80.0432,36.0626]]},{"name":"State Senate District 31","center":[-80.2321,36.1575],"bounds":[[-80.4527,35.9966],[-80.0273,36.5506]]},{"name":"State Senate District 32","center":[-80.3342,36.0947],"bounds":[[-80.5167,35.9728],[-80.1942,36.1838]]},{"name":"State Senate District 33","center":[-80.3573,35.4467],"bounds":[[-80.7716,35.1431],[-80.0512,35.8635]]},{"name":"State Senate District 34","center":[-80.604,35.3599],"bounds":[[-80.7871,35.2218],[-80.2954,35.5064]]},{"name":"State Senate District 35","center":[-80.5586,35.0741],"bounds":[[-80.8404,34.8355],[-80.2768,35.3293]]},{"name":"State Senate District 36","center":[-81.1037,36.1627],"bounds":[[-81.5455,35.7766],[-80.4322,36.5623]]},{"name":"State Senate District 37","center":[-80.9387,35.6108],"bounds":[[-81.1095,35.4006],[-80.6932,36.0588]]},{"name":"State Senate District 38","center":[-80.7902,35.2764],"bounds":[[-80.8684,35.177],[-80.6937,35.4002]]},{"name":"State Senate District 39","center":[-80.9084,35.1467],"bounds":[[-81.058,35.0447],[-80.7901,35.2247]]},{"name":"State Senate District 40","center":[-80.7033,35.2371],"bounds":[[-80.7812,35.1034],[-80.5503,35.3467]]},{"name":"State Senate District 41","center":[-80.9034,35.336],"bounds":[[-81.015,35.1713],[-80.7522,35.5125]]},{"name":"State Senate District 42","center":[-80.8131,35.0941],"bounds":[[-80.8981,35.0016],[-80.6814,35.1842]]},{"name":"State Senate District 43","center":[-81.1214,35.2902],"bounds":[[-81.3649,35.1484],[-80.923,35.4108]]},{"name":"State Senate District 44","center":[-81.3419,35.4113],"bounds":[[-81.7681,35.1634],[-80.9397,35.5846]]},{"name":"State Senate District 45","center":[-81.3101,35.7961],"bounds":[[-81.5918,35.547],[-80.9252,35.9968]]},{"name":"State Senate District 46","center":[-82.1119,35.7004],"bounds":[[-82.6095,35.4579],[-81.3638,35.9999]]},{"name":"State Senate District 47","center":[-82.1587,35.9601],"bounds":[[-83.0994,35.4705],[-80.9017,36.5881]]},{"name":"State Senate District 48","center":[-82.2874,35.3828],"bounds":[[-82.7451,35.1437],[-81.692,35.6136]]},{"name":"State Senate District 49","center":[-82.6459,35.5945],"bounds":[[-82.8881,35.4165],[-82.4483,35.7628]]},{"name":"State Senate District 50","center":[-83.3101,35.42],"bounds":[[-84.3219,34.9866],[-82.5742,35.7751]]}],"state_house":[{"name":"State House District 1","center":[-76.2232,36.079],"bounds":[[-76.8473,35.598],[-75.6441,36.5507]]},{"name":"State House District 2","center":[-78.8886,36.1198],"bounds":[[-79.154,36.006],[-78.7513,36.5422]]},{"name":"State House District 3","center":[-77.093,35.1326],"bounds":[[-77.4737,34.874],[-76.8517,35.4184]]},{"name":"State House District 4","center":[-78.0257,35.0828],"bounds":[[-78.3066,34.7102],[-77.6511,35.3803]]},{"name":"State House District 5","center":[-76.4915,36.3444],"bounds":[[-77.2086,36.1235],[-75.9126,36.5521]]},{"name":"State House District 6","center":[-78.853,35.3262],"bounds":[[-79.223,35.1921],[-78.6831,35.5215]]},{"name":"State House District 7","center":[-78.3723,36.125],"bounds":[[-78.7177,35.8181],[-78.0066,36.2662]]},{"name":"State House District 8","center":[-77.3054,35.6257],"bounds":[[-77.7007,35.4726],[-77.0846,35.8331]]},{"name":"State House District 9","center":[-77.3757,35.4631],"bounds":[[-77.5118,35.3277],[-77.1738,35.6073]]},{"name":"State House District 10","center":[-77.9937,35.374],"bounds":[[-78.1624,35.3138],[-77.7999,35.5978]]},{"name":"State House District 11","center":[-78.726,35.7264],"bounds":[[-78.809,35.6598],[-78.6492,35.8005]]},{"name":"State House District 12","center":[-77.3732,35.1539],"bounds":[[-77.8342,34.7803],[-77.0472,35.6523]]},{"name":"State House District 13","center":[-76.6585,34.7961],"bounds":[[-77.1678,34.5916],[-76.0367,35.0764]]},{"name":"State House District 14","center":[-77.2855,34.7115],"bounds":[[-77.5228,34.5303],[-77.1052,34.8555]]},{"name":"State House District 15","center":[-77.3659,34.8205],"bounds":[[-77.6801,34.6951],[-77.2006,34.9845]]},{"name":"State House District 16","center":[-77.9065,34.511],"bounds":[[-78.2726,34.2926],[-77.3366,34.7338]]},{"name":"State House District 17","center":[-78.2905,34.0733],"bounds":[[-78.6504,33.8527],[-77.9322,34.3717]]},{"name":"State House District 18","center":[-77.8988,34.3015],"bounds":[[-78.0299,34.1913],[-77.7105,34.3894]]},{"name":"State House District 19","center":[-78.1627,34.0104],"bounds":[[-78.3831,33.8423],[-77.8579,34.1991]]},{"name":"State House District 20","center":[-77.8633,34.224],"bounds":[[-77.926,34.1096],[-77.7647,34.2771]]},{"name":"State House District 21","center":[-78.8578,35.8061],"bounds":[[-78.9363,35.7603],[-78.7802,35.8709]]},{"name":"State House District 22","center":[-78.6084,34.8274],"bounds":[[-78.902,34.3676],[-78.1134,35.3164]]},{"name":"State House District 23","center":[-77.2817,35.9995],"bounds":[[-77.8284,35.6588],[-76.6819,36.2466]]},{"name":"State House District 24","center":[-77.9423,35.7855],"bounds":[[-78.1921,35.5835],[-77.6651,35.9189]]},{"name":"State House District 25","center":[-77.9408,36.0071],"bounds":[[-78.257,35.7279],[-77.698,36.2026]]},{"name":"State House District 26","center":[-78.3562,35.6672],"bounds":[[-78.5879,35.5516],[-78.1513,35.8181]]},{"name":"State House District 27","center":[-77.6108,36.2245],"bounds":[[-78.324,36.0036],[-77.0662,36.5473]]},{"name":"State House District 28","center":[-78.3871,35.4548],"bounds":[[-78.6148,35.2547],[-78.0648,35.6692]]},{"name":"State House District 29","center":[-78.9315,35.9414],"bounds":[[-79.0163,35.8632],[-78.8875,35.9869]]},{"name":"State House District 30","center":[-78.9131,36.0224],"bounds":[[-79.0007,35.9509],[-78.8405,36.0728]]},{"name":"State House District 31","center":[-78.8373,35.9584],"bounds":[[-78.9194,35.867],[-78.6998,36.0478]]},{"name":"State House District 32","center":[-78.6025,36.2091],"bounds":[[-78.8075,36.0696],[-78.2772,36.5438]]},{"name":"State House District 33","center":[-78.6096,35.6969],"bounds":[[-78.6994,35.5301],[-78.4737,35.7579]]},{"name":"State House District 34","center":[-78.6476,35.8559],"bounds":[[-78.6988,35.7884],[-78.6007,35.9248]]},{"name":"State House District 35","center":[-78.5092,35.9192],"bounds":[[-78.5801,35.8543],[-78.3868,36.0243]]},{"name":"State House District 36","center":[-78.8585,35.7026],"bounds":[[-78.995,35.5921],[-78.7769,35.7789]]},{"name":"State House District 37","center":[-78.775,35.6312],"bounds":[[-78.9391,35.5195],[-78.6809,35.7002]]},{"name":"State House District 38","center":[-78.6017,35.767],"bounds":[[-78.6804,35.7238],[-78.5316,35.834]]},{"name":"State House District 39","center":[-78.4415,35.8263],"bounds":[[-78.5658,35.7015],[-78.2538,35.9365]]},{"name":"State House District 40","center":[-78.6536,35.932],"bounds":[[-78.802,35.8621],[-78.5529,36.0764]]},{"name":"State House District 41","center":[-78.807,35.7718],"bounds":[[-78.8771,35.7264],[-78.7354,35.8054]]},{"name":"State House District 42","center":[-78.9796,35.1155],"bounds":[[-79.1129,34.9998],[-78.83,35.2316]]},{"name":"State House District 43","center":[-78.7361,35.0759],"bounds":[[-78.9329,34.8349],[-78.4947,35.2669]]},{"name":"State House District 44","center":[-78.9432,35.058],"bounds":[[-79.0114,34.9995],[-78.8785,35.1283]]},{"name":"State House District 45","center":[-78.9593,34.9928],"bounds":[[-79.0568,34.893],[-78.8673,35.0589]]},{"name":"State House District 46","center":[-78.7525,34.4302],"bounds":[[-79.1308,33.9443],[-78.1623,34.9527]]},{"name":"State House District 47","center":[-79.1292,34.6503],"bounds":[[-79.4616,34.3309],[-78.936,34.8811]]},{"name":"State House District 48","center":[-79.3104,35.0067],"bounds":[[-79.6929,34.6303],[-79.0348,35.2138]]},{"name":"State House District 49","center":[-78.7448,35.837],"bounds":[[-78.8283,35.771],[-78.6554,35.9276]]},{"name":"State House District 50","center":[-79.177,36.0776],"bounds":[[-79.5319,35.864],[-78.9506,36.5417]]},{"name":"State House District 51","center":[-79.2295,35.3531],"bounds":[[-79.5447,35.1613],[-78.9696,35.6283]]},{"name":"State House District 52","center":[-79.6381,35.098],"bounds":[[-80.0757,34.805],[-79.2983,35.2908]]},{"name":"State House District 53","center":[-78.6356,35.448],"bounds":[[-78.9698,35.2457],[-78.4529,35.6126]]},{"name":"State House District 54","center":[-79.2643,35.6822],"bounds":[[-79.6457,35.515],[-78.9061,35.9034]]},{"name":"State House District 55","center":[-80.318,35.0228],"bounds":[[-80.7975,34.8066],[-79.8485,35.2111]]},{"name":"State House District 56","center":[-79.0851,35.9296],"bounds":[[-79.1441,35.8608],[-79.0007,35.9866]]},{"name":"State House District 57","center":[-79.8411,36.1513],"bounds":[[-79.9681,36.0956],[-79.7414,36.2546]]},{"name":"State House District 58","center":[-79.832,36.0151],"bounds":[[-79.9383,35.9101],[-79.7128,36.0677]]},{"name":"State House District 59","center":[-79.7193,36.0757],"bounds":[[-79.797,35.8999],[-79.5324,36.2487]]},{"name":"State House District 60","center":[-79.955,35.9877],"bounds":[[-80.0469,35.9129],[-79.8546,36.0412]]},{"name":"State House District 61","center":[-79.7987,36.0762],"bounds":[[-79.9,36.0357],[-79.7258,36.1113]]},{"name":"State House District 62","center":[-79.952,36.1011],"bounds":[[-80.0438,35.9924],[-79.8381,36.2572]]},{"name":"State House District 63","center":[-79.3671,36.0737],"bounds":[[-79.4769,35.9931],[-79.258,36.2476]]},{"name":"State House District 64","center":[-79.3906,36.0316],"bounds":[[-79.5424,35.8433],[-79.2366,36.2497]]},{"name":"State House District 65","center":[-79.7824,36.3962],"bounds":[[-80.0351,36.2415],[-79.5136,36.5428]]},{"name":"State House District 66","center":[-78.5564,35.8678],"bounds":[[-78.6275,35.8143],[-78.5066,35.9091]]},{"name":"State House District 67","center":[-80.0726,35.2071],"bounds":[[-80.5062,35.1372],[-79.6143,35.5115]]},{"name":"State House District 68","center":[-80.6967,34.9923],"bounds":[[-80.8404,34.8999],[-80.5673,35.0728]]},{"name":"State House District 69","center":[-80.5702,35.0626],"bounds":[[-80.7365,34.99],[-80.3908,35.2084]]},{"name":"State House District 70","center":[-79.841,35.7808],"bounds":[[-80.0582,35.6501],[-79.7579,35.9207]]},{"name":"State House District 71","center":[-80.2634,36.0607],"bounds":[[-80.342,35.9944],[-80.1814,36.1061]]},{"name":"State House District 72","center":[-80.253,36.1266],"bounds":[[-80.3587,36.0883],[-80.1585,36.1936]]},{"name":"State House District 73","center":[-80.625,35.3556],"bounds":[[-80.7664,35.2487],[-80.5039,35.4346]]},{"name":"State House District 74","center":[-80.3846,36.0892],"bounds":[[-80.5167,35.9728],[-80.2935,36.1838]]},{"name":"State House District 75","center":[-80.1649,36.0908],"bounds":[[-80.2669,35.9966],[-80.037,36.1844]]},{"name":"State House District 76","center":[-80.4082,35.6577],"bounds":[[-80.5984,35.502],[-80.1829,35.7862]]},{"name":"State House District 77","center":[-80.5503,36.0045],"bounds":[[-80.8816,35.6073],[-80.3652,36.2879]]},{"name":"State House District 78","center":[-79.6295,35.449],"bounds":[[-80.0668,35.1201],[-79.3989,35.9088]]},{"name":"State House District 79","center":[-76.2987,35.4913],"bounds":[[-77.1958,34.9638],[-75.4606,36.0525]]},{"name":"State House District 80","center":[-80.1812,35.8109],"bounds":[[-80.2595,35.5041],[-80.0432,36.0268]]},{"name":"State House District 81","center":[-80.307,35.8182],"bounds":[[-80.4874,35.6195],[-80.1487,35.9967]]},{"name":"State House District 82","center":[-80.6644,35.4313],"bounds":[[-80.7871,35.3595],[-80.567,35.5064]]},{"name":"State House District 83","center":[-80.5647,35.4133],"bounds":[[-80.7555,35.185],[-80.2954,35.6524]]},{"name":"State House District 84","center":[-80.9269,35.7693],"bounds":[[-81.1095,35.6355],[-80.6932,36.0588]]},{"name":"State House District 85","center":[-82.1197,35.9063],"bounds":[[-82.5055,35.518],[-81.7357,36.2871]]},{"name":"State House District 86","center":[-81.7246,35.7643],"bounds":[[-81.9869,35.5583],[-81.3638,35.9999]]},{"name":"State House District 87","center":[-81.5649,35.9998],"bounds":[[-81.8105,35.7572],[-81.3283,36.2042]]},{"name":"State House District 88","center":[-80.912,35.1927],"bounds":[[-81.0143,35.1355],[-80.8272,35.2478]]},{"name":"State House District 89","center":[-81.1752,35.6822],"bounds":[[-81.5354,35.547],[-80.8677,35.829]]},{"name":"State House District 90","center":[-80.824,36.3072],"bounds":[[-81.1006,36.12],[-80.4403,36.5623]]},{"name":"State House District 91","center":[-80.2671,36.243],"bounds":[[-80.4527,36.1491],[-80.0273,36.5506]]},{"name":"State House District 92","center":[-80.9507,35.124],"bounds":[[-81.058,35.0447],[-80.8753,35.1939]]},{"name":"State House District 93","center":[-81.5347,36.3368],"bounds":[[-81.9181,36.1115],[-80.9017,36.5881]]},{"name":"State House District 94","center":[-81.2275,36.1346],"bounds":[[-81.5455,35.7766],[-80.8788,36.4404]]},{"name":"State House District 95","center":[-80.8705,35.5738],"bounds":[[-80.9635,35.4885],[-80.7363,35.6467]]},{"name":"State House District 96","center":[-81.2955,35.7035],"bounds":[[-81.4761,35.6296],[-81.1789,35.8233]]},{"name":"State House District 97","center":[-81.1388,35.4799],"bounds":[[-81.5376,35.4001],[-80.9397,35.5681]]},{"name":"State House District 98","center":[-80.8686,35.4342],"bounds":[[-80.9587,35.3756],[-80.7567,35.5148]]},{"name":"State House District 99","center":[-80.7249,35.2815],"bounds":[[-80.7952,35.2317],[-80.6661,35.3467]]},{"name":"State House District 100","center":[-80.7501,35.1893],"bounds":[[-80.8125,35.134],[-80.7068,35.2321]]},{"name":"State House District 101","center":[-80.9259,35.2845],"bounds":[[-81.015,35.2223],[-80.8522,35.3514]]},{"name":"State House District 102","center":[-80.8101,35.23],"bounds":[[-80.8684,35.1924],[-80.7399,35.2787]]},{"name":"State House District 103","center":[-80.7533,35.1026],"bounds":[[-80.8245,35.0277],[-80.6542,35.1733]]},{"name":"State House District 104","center":[-80.8194,35.1417],"bounds":[[-80.8812,35.0829],[-80.7604,35.2025]]},{"name":"State House District 105","center":[-80.8431,35.0721],"bounds":[[-80.8981,35.0016],[-80.7878,35.12]]},{"name":"State House District 106","center":[-80.785,35.3664],"bounds":[[-80.8627,35.2787],[-80.6937,35.4414]]},{"name":"State House District 107","center":[-80.8755,35.3404],"bounds":[[-80.9868,35.2495],[-80.7618,35.4154]]},{"name":"State House District 108","center":[-81.0928,35.3153],"bounds":[[-81.2716,35.2258],[-80.923,35.4098]]},{"name":"State House District 109","center":[-81.1285,35.217],"bounds":[[-81.269,35.1484],[-81.0024,35.2722]]},{"name":"State House District 110","center":[-81.4133,35.3408],"bounds":[[-81.7073,35.1611],[-81.1587,35.5846]]},{"name":"State House District 111","center":[-81.6956,35.351],"bounds":[[-81.971,35.1634],[-81.3217,35.6136]]},{"name":"State House District 112","center":[-80.6835,35.2088],"bounds":[[-80.7399,35.125],[-80.5503,35.2677]]},{"name":"State House District 113","center":[-82.1589,35.3669],"bounds":[[-82.5009,35.1814],[-81.8064,35.696]]},{"name":"State House District 114","center":[-82.4226,35.628],"bounds":[[-82.5798,35.4579],[-82.169,35.824]]},{"name":"State House District 115","center":[-82.6186,35.509],"bounds":[[-82.7995,35.4165],[-82.4483,35.602]]},{"name":"State House District 116","center":[-82.6447,35.6589],"bounds":[[-82.8881,35.5628],[-82.4052,35.8033]]},{"name":"State House District 117","center":[-82.4684,35.3284],"bounds":[[-82.7451,35.1437],[-82.2613,35.5002]]},{"name":"State House District 118","center":[-82.8467,35.6766],"bounds":[[-83.2561,35.2916],[-82.4086,36.0658]]},{"name":"State House District 119","center":[-83.2469,35.3597],"bounds":[[-83.9529,35.0014],[-82.5742,35.6961]]},{"name":"State House District 120","center":[-83.6302,35.272],"bounds":[[-84.3219,34.9866],[-83.1084,35.4665]]}],"county":[{"name":"Alamance","center":[-79.3551,36.0309],"bounds":[[-79.5424,35.8433],[-79.2366,36.2497]]},{"name":"Alexander","center":[-81.2044,35.9106],"bounds":[[-81.344,35.7766],[-81.0034,36.0457]]},{"name":"Alleghany","center":[-81.1735,36.4585],"bounds":[[-81.3533,36.3661],[-80.9017,36.575]]},{"name":"Anson","center":[-80.0504,35.0482],"bounds":[[-80.3208,34.8066],[-79.8485,35.2111]]},{"name":"Ashe","center":[-81.4713,36.4057],"bounds":[[-81.742,36.2403],[-81.2442,36.5881]]},{"name":"Avery","center":[-81.917,36.0948],"bounds":[[-82.081,35.9114],[-81.7357,36.2871]]},{"name":"Beaufort","center":[-76.8878,35.5369],"bounds":[[-77.1958,35.2161],[-76.4689,35.7395]]},{"name":"Bertie","center":[-77.0428,35.9918],"bounds":[[-77.328,35.8119],[-76.6819,36.2466]]},{"name":"Bladen","center":[-78.5353,34.6368],"bounds":[[-78.902,34.3676],[-78.1765,34.8562]]},{"name":"Brunswick","center":[-78.3346,34.1104],"bounds":[[-78.6504,33.8423],[-77.931,34.3717]]},{"name":"Buncombe","center":[-82.5763,35.6031],"bounds":[[-82.8881,35.4165],[-82.169,35.824]]},{"name":"Burke","center":[-81.7246,35.7643],"bounds":[[-81.9869,35.5583],[-81.3638,35.9999]]},{"name":"Cabarrus","center":[-80.6166,35.3694],"bounds":[[-80.7871,35.185],[-80.2954,35.5064]]},{"name":"Caldwell","center":[-81.5484,35.9552],"bounds":[[-81.8105,35.7572],[-81.3283,36.1226]]},{"name":"Camden","center":[-76.1674,36.3515],"bounds":[[-76.5415,36.1646],[-75.9126,36.551]]},{"name":"Carteret","center":[-76.6432,34.7898],"bounds":[[-77.1678,34.5916],[-76.0367,35.0764]]},{"name":"Caswell","center":[-79.3415,36.4239],"bounds":[[-79.5319,36.2419],[-79.1383,36.5417]]},{"name":"Catawba","center":[-81.1541,35.7091],"bounds":[[-81.5354,35.547],[-80.9252,35.829]]},{"name":"Chatham","center":[-79.1794,35.6486],"bounds":[[-79.5558,35.515],[-78.9061,35.8768]]},{"name":"Cherokee","center":[-83.9243,35.1824],"bounds":[[-84.3219,34.9873],[-83.6902,35.2922]]},{"name":"Chowan","center":[-76.5965,36.1918],"bounds":[[-76.7223,36.0065],[-76.4081,36.3511]]},{"name":"Clay","center":[-83.7359,35.0886],"bounds":[[-84.0058,34.9866],[-83.483,35.1612]]},{"name":"Cleveland","center":[-81.5426,35.3982],"bounds":[[-81.7681,35.1634],[-81.3217,35.5846]]},{"name":"Columbus","center":[-78.6847,34.2468],"bounds":[[-79.0712,33.9443],[-78.1623,34.4848]]},{"name":"Craven","center":[-77.0693,35.1218],"bounds":[[-77.4737,34.8089],[-76.6526,35.4184]]},{"name":"Cumberland","center":[-78.7616,35.0779],"bounds":[[-79.1129,34.8349],[-78.4947,35.2669]]},{"name":"Currituck","center":[-75.9482,36.3333],"bounds":[[-76.3133,36.0722],[-75.7733,36.5507]]},{"name":"Dare","center":[-75.682,35.7116],"bounds":[[-76.013,35.1965],[-75.4606,36.2315]]},{"name":"Davidson","center":[-80.3053,35.7974],"bounds":[[-80.4874,35.5041],[-80.0432,36.0268]]},{"name":"Davie","center":[-80.5016,35.8671],"bounds":[[-80.7078,35.7428],[-80.3652,36.0626]]},{"name":"Duplin","center":[-77.9739,34.907],"bounds":[[-78.1986,34.7102],[-77.6511,35.1937]]},{"name":"Durham","center":[-78.8551,35.9857],"bounds":[[-79.0163,35.8632],[-78.6998,36.2393]]},{"name":"Edgecombe","center":[-77.5887,36.0339],"bounds":[[-77.8284,35.6749],[-77.3424,36.1545]]},{"name":"Forsyth","center":[-80.3142,36.1171],"bounds":[[-80.5167,35.9728],[-80.0351,36.2615]]},{"name":"Franklin","center":[-78.2462,36.1096],"bounds":[[-78.5464,35.8181],[-78.0066,36.2662]]},{"name":"Gaston","center":[-81.1064,35.2938],"bounds":[[-81.4556,35.1484],[-80.923,35.4198]]},{"name":"Gates","center":[-76.7783,36.4009],"bounds":[[-76.9505,36.2961],[-76.4537,36.5521]]},{"name":"Graham","center":[-83.8177,35.3457],"bounds":[[-84.0383,35.2169],[-83.5824,35.4665]]},{"name":"Granville","center":[-78.6113,36.3406],"bounds":[[-78.8075,36.0218],[-78.4535,36.5425]]},{"name":"Greene","center":[-77.5918,35.4632],"bounds":[[-77.8267,35.3473],[-77.4743,35.6523]]},{"name":"Guilford","center":[-79.8608,36.0529],"bounds":[[-80.0469,35.8999],[-79.5324,36.2572]]},{"name":"Halifax","center":[-77.6247,36.2083],"bounds":[[-78.0066,36.0036],[-77.2302,36.512]]},{"name":"Harnett","center":[-78.7798,35.3202],"bounds":[[-79.223,35.1921],[-78.5299,35.5841]]},{"name":"Haywood","center":[-82.9845,35.5514],"bounds":[[-83.2561,35.2916],[-82.7451,35.7917]]},{"name":"Henderson","center":[-82.4695,35.3409],"bounds":[[-82.7451,35.1437],[-82.2613,35.5002]]},{"name":"Hertford","center":[-76.9909,36.4458],"bounds":[[-77.2086,36.2381],[-76.6938,36.5463]]},{"name":"Hoke","center":[-79.241,35.0621],"bounds":[[-79.4588,34.8337],[-79.0348,35.2138]]},{"name":"Hyde","center":[-76.2194,35.4682],"bounds":[[-76.6375,35.066],[-75.7736,35.7052]]},{"name":"Iredell","center":[-80.947,35.6917],"bounds":[[-81.1095,35.4885],[-80.6932,36.0588]]},{"name":"Jackson","center":[-83.1508,35.2854],"bounds":[[-83.3637,35.0014],[-82.9192,35.526]]},{"name":"Johnston","center":[-78.3497,35.5255],"bounds":[[-78.7089,35.2547],[-78.0648,35.8181]]},{"name":"Jones","center":[-77.222,34.9151],"bounds":[[-77.731,34.7803],[-77.0472,35.243]]},{"name":"Lee","center":[-79.2289,35.5102],"bounds":[[-79.3599,35.3072],[-78.9696,35.6283]]},{"name":"Lenoir","center":[-77.5418,35.3355],"bounds":[[-77.8342,35.0081],[-77.3908,35.4268]]},{"name":"Lincoln","center":[-81.1388,35.4799],"bounds":[[-81.5376,35.4001],[-80.9397,35.5681]]},{"name":"Macon","center":[-83.4435,35.1629],"bounds":[[-83.7381,34.9935],[-83.1084,35.331]]},{"name":"Madison","center":[-82.7047,35.8457],"bounds":[[-82.9629,35.6782],[-82.4086,36.0658]]},{"name":"Martin","center":[-77.0341,35.8715],"bounds":[[-77.4092,35.6588],[-76.7606,36.0714]]},{"name":"McDowell","center":[-82.0649,35.7603],"bounds":[[-82.2949,35.518],[-81.8241,35.9601]]},{"name":"Mecklenburg","center":[-80.865,35.2616],"bounds":[[-81.058,35.0016],[-80.5503,35.5148]]},{"name":"Mitchell","center":[-82.1915,35.9926],"bounds":[[-82.4167,35.8227],[-81.979,36.1591]]},{"name":"Montgomery","center":[-79.8841,35.2684],"bounds":[[-80.1826,35.1372],[-79.6143,35.5115]]},{"name":"Moore","center":[-79.3846,35.2377],"bounds":[[-79.768,35.043],[-79.0958,35.518]]},{"name":"Nash","center":[-77.9498,36.0233],"bounds":[[-78.257,35.7279],[-77.698,36.2026]]},{"name":"New Hanover","center":[-77.9101,34.2681],"bounds":[[-78.0299,33.9292],[-77.7105,34.3894]]},{"name":"Northampton","center":[-77.4018,36.4043],"bounds":[[-77.9001,36.1649],[-77.0662,36.5473]]},{"name":"Onslow","center":[-77.262,34.7494],"bounds":[[-77.6801,34.4409],[-77.1052,34.9845]]},{"name":"Orange","center":[-79.1503,36.0201],"bounds":[[-79.2684,35.8608],[-78.9506,36.2434]]},{"name":"Pamlico","center":[-76.7284,35.1498],"bounds":[[-76.9875,34.9638],[-76.4674,35.3355]]},{"name":"Pasquotank","center":[-76.2849,36.3202],"bounds":[[-76.4914,36.1235],[-76.0593,36.5107]]},{"name":"Pender","center":[-77.9985,34.4767],"bounds":[[-78.2726,34.2926],[-77.5184,34.7326]]},{"name":"Perquimans","center":[-76.3969,36.1804],"bounds":[[-76.5901,36.0749],[-76.1917,36.3781]]},{"name":"Person","center":[-78.9731,36.4001],"bounds":[[-79.154,36.2358],[-78.7948,36.5422]]},{"name":"Pitt","center":[-77.3215,35.5567],"bounds":[[-77.7007,35.3277],[-77.0846,35.8331]]},{"name":"Polk","center":[-82.1748,35.307],"bounds":[[-82.3593,35.1848],[-81.9628,35.4094]]},{"name":"Randolph","center":[-79.8621,35.7879],"bounds":[[-80.0668,35.5057],[-79.5417,35.9207]]},{"name":"Richmond","center":[-79.7433,35.0296],"bounds":[[-80.0757,34.805],[-79.4588,35.1839]]},{"name":"Robeson","center":[-78.9918,34.5758],"bounds":[[-79.4616,34.2993],[-78.8054,34.9527]]},{"name":"Rockingham","center":[-79.7824,36.3962],"bounds":[[-80.0351,36.2415],[-79.5136,36.5428]]},{"name":"Rowan","center":[-80.4936,35.6972],"bounds":[[-80.7716,35.502],[-80.1829,35.8635]]},{"name":"Rutherford","center":[-81.9912,35.4343],"bounds":[[-82.2805,35.1804],[-81.692,35.6136]]},{"name":"Sampson","center":[-78.4714,34.9065],"bounds":[[-78.6723,34.5536],[-78.1134,35.3164]]},{"name":"Scotland","center":[-79.4534,34.8841],"bounds":[[-79.6929,34.6303],[-79.3311,35.0436]]},{"name":"Stanly","center":[-80.2426,35.24],"bounds":[[-80.5062,35.1431],[-80.0512,35.5042]]},{"name":"Stokes","center":[-80.2945,36.3639],"bounds":[[-80.4519,36.2572],[-80.0273,36.5506]]},{"name":"Surry","center":[-80.7195,36.3386],"bounds":[[-80.9736,36.2363],[-80.4403,36.5623]]},{"name":"Swain","center":[-83.4918,35.4778],"bounds":[[-83.9529,35.2792],[-83.156,35.6961]]},{"name":"Transylvania","center":[-82.8229,35.1914],"bounds":[[-83.0569,35.0276],[-82.5742,35.423]]},{"name":"Tyrrell","center":[-76.1736,35.7397],"bounds":[[-76.406,35.598],[-76.0114,35.9948]]},{"name":"Union","center":[-80.5504,35.0628],"bounds":[[-80.8404,34.8141],[-80.2768,35.2084]]},{"name":"Vance","center":[-78.4464,36.3566],"bounds":[[-78.5112,36.1637],[-78.2772,36.5438]]},{"name":"Wake","center":[-78.6166,35.8306],"bounds":[[-78.995,35.5195],[-78.2538,36.0764]]},{"name":"Warren","center":[-78.0954,36.2885],"bounds":[[-78.324,36.2026],[-77.8995,36.5447]]},{"name":"Washington","center":[-76.6852,35.8458],"bounds":[[-76.8473,35.6976],[-76.3536,35.9821]]},{"name":"Watauga","center":[-81.7388,36.2684],"bounds":[[-81.9181,36.1115],[-81.4558,36.3912]]},{"name":"Wayne","center":[-78.0516,35.3083],"bounds":[[-78.3066,35.1466],[-77.7999,35.5978]]},{"name":"Wilkes","center":[-81.2446,36.2073],"bounds":[[-81.5455,35.9948],[-80.8687,36.4404]]},{"name":"Wilson","center":[-77.9848,35.7213],"bounds":[[-78.1921,35.5835],[-77.6651,35.8672]]},{"name":"Yadkin","center":[-80.6157,36.2122],"bounds":[[-80.8816,36.0465],[-80.4322,36.2879]]},{"name":"Yancey","center":[-82.2864,35.9008],"bounds":[[-82.5055,35.6987],[-82.1335,36.0845]]}]}}